dki-0.1.2.dist-info/METADATA
dki-0.1.2.dist-info/WHEEL
dki-0.1.2.dist-info/entry_points.txt
dki/__init__.py
dki/cli.py
dki/libs.py
dki-0.1.2.dist-info/RECORD
