Metadata-Version: 2.1
Name: dki
Version: 0.1.2
Summary: docker image build and pull tools
Author-Email: svtter <svtter@qq.com>
License: MIT
Requires-Python: >=3.9
Requires-Dist: click>=8.1.8
